{
    "session_id": "ws_1747780686985_e8qhdu9ol",
    "origem": "whatsapp",
    "versao": "v1-main",
    "timestamp": "2025-05-20 22:38:04",
    "criado_em": 1747780684,
    "Rec": true,
    "etapa_atual": "confirmar_endereco",
    "NOME": "Maria de F\u00e1tima lima",
    "ultima_atualizacao": "2025-05-20 22:52:24",
    "CONTATO": "973 957277",
    "PROBLEMA_RELATADO": "Flacidez,,cara de budog,,bigode chines",
    "marcos_progresso": [
        "audio_introdutorio",
        "entrega",
        "perguntas"
    ],
    "PERGUNTAS_FEITAS": [
        "1 mes",
        "S\u00f3 posso pedir em 6\/5",
        "Sim"
    ],
    "ENDERE\u00c7O": "4900-082"
}