{
    "session_id": "ws_1747841350925_qri734ey0",
    "origem": "whatsapp",
    "versao": "v1-main",
    "timestamp": "2025-05-21 15:29:09",
    "criado_em": 1747841349,
    "Rec": true,
    "etapa_atual": "perguntas",
    "NOME": "Ol\u00e1 Douquanto custator quanto custa o suplemento ?",
    "ultima_atualizacao": "2025-05-21 15:43:11",
    "CONTATO": "934979562 WhatsApp",
    "PROBLEMA_RELATADO": "E para algu\u00e9m com 58 anos",
    "marcos_progresso": [
        "audio_introdutorio",
        "entrega",
        "perguntas"
    ],
    "PERGUNTAS_FEITAS": [
        "Okay obrigado"
    ],
    "CONVERSA_IA": []
}